conflagrate/__init__.py
conflagrate/__version__.py
conflagrate/asyncutils.py
conflagrate/controlflow.py
conflagrate/dependencies.py
conflagrate/engine.py
conflagrate/graph.py
conflagrate/registration.py
conflagrate/parse/__init__.py
conflagrate/parse/graphviz.py
conflagrate/parse/native.py
conflagrate-0.1.2.dist-info/LICENSE
conflagrate-0.1.2.dist-info/METADATA
conflagrate-0.1.2.dist-info/WHEEL
conflagrate-0.1.2.dist-info/top_level.txt
conflagrate-0.1.2.dist-info/RECORD
