Metadata-Version: 2.1
Name: conflagrate
Version: 0.1.2
Summary: A framework for writing applications with control flow graphs
Home-page: https://github.com/ignirtoq/conflagrate
Author: Jeffrey Bouas
Author-email: ignirtoq+conflagrate@gmail.com
License: MIT
Project-URL: Bug Tracker, https://github.com/ignirtoq/conflagrate/issues
Project-URL: Source Code, https://github.com/ignirtoq/conflagrate
Platform: UNKNOWN
Classifier: Development Status :: 4 - Beta
Classifier: Intended Audience :: Developers
Classifier: License :: OSI Approved :: MIT License
Classifier: Operating System :: OS Independent
Classifier: Programming Language :: Python
Classifier: Programming Language :: Python :: 3 :: Only
Classifier: Programming Language :: Python :: 3.8
Classifier: Programming Language :: Python :: 3.9
Classifier: Programming Language :: Python :: 3.10
Classifier: Programming Language :: Python :: 3.11
Classifier: Topic :: Software Development
Classifier: Topic :: Software Development :: Libraries
Classifier: Topic :: Software Development :: Libraries :: Application Frameworks
Requires-Python: >=3.8
License-File: LICENSE
Requires-Dist: pydot (~=1.4)
